configutility/__init__.py
configutility-0.0.1.dist-info/LICENCE.txt
configutility-0.0.1.dist-info/METADATA
configutility-0.0.1.dist-info/WHEEL
configutility-0.0.1.dist-info/top_level.txt
configutility-0.0.1.dist-info/RECORD
